{
    "V": [
        "v1",
        "v2"
    ],
    "U": [
        "u1"
    ],
    "K": [
        "k1",
        "k2"
    ],
    "carriers": [
        "l1",
        "l2"
    ],
    "S": {
        "v1": 2246,
        "v2": 4641
    },
    "D": {
        "u1": 415
    },
    "L": {
        "l1": 1,
        "l2": 2
    },
    "costs": {
        "l1": {
            "v1,u1": 411,
            "v2,u1": 197
        },
        "l2": {
            "v1,u1": 232,
            "v2,u1": 666
        }
    },
    "T": {
        "v1": "k1",
        "v2": "k2",
        "u1": "k1"
    }
}